streamlit_connection/__init__.py
streamlit_connection/mysqlconnection.py
example_streamlit_mysql_connection_noah2-0.0.1.dist-info/LICENSE.txt
example_streamlit_mysql_connection_noah2-0.0.1.dist-info/METADATA
example_streamlit_mysql_connection_noah2-0.0.1.dist-info/WHEEL
example_streamlit_mysql_connection_noah2-0.0.1.dist-info/top_level.txt
example_streamlit_mysql_connection_noah2-0.0.1.dist-info/RECORD
